csvcubedmodels/__init__.py
csvcubedmodels/dataclassbase.py
csvcubedmodels/rdf/__init__.py
csvcubedmodels/rdf/datatypes.py
csvcubedmodels/rdf/dcat.py
csvcubedmodels/rdf/dependency.py
csvcubedmodels/rdf/namespaces.py
csvcubedmodels/rdf/qb.py
csvcubedmodels/rdf/rdf.py
csvcubedmodels/rdf/rdfs.py
csvcubedmodels/rdf/resource.py
csvcubedmodels/rdf/skos.py
csvcubedmodels/rdf/triple.py
csvcubedmodels/scripts/__init__.py
csvcubedmodels/scripts/rdfmodelgeneration/__init__.py
csvcubedmodels/scripts/rdfmodelgeneration/generateqbstructure.py
csvcubedmodels/scripts/rdfmodelgeneration/generateskosstructure.py
csvcubedmodels/scripts/rdfmodelgeneration/tools.py
csvcubedmodels/utils/__init__.py
csvcubedmodels/utils/uri.py
csvcubed_models-0.1.10.dist-info/LICENSE
csvcubed_models-0.1.10.dist-info/METADATA
csvcubed_models-0.1.10.dist-info/WHEEL
csvcubed_models-0.1.10.dist-info/RECORD
