Metadata-Version: 2.1
Name: csvcubed-models
Version: 0.1.10
Summary: Models and RDF serialisation functionality useful to the csvcubed family of tools.
License: Apache-2.0
Author: Integrated Data Service - Dissemination
Author-email: csvcubed@gsscogs.uk
Requires-Python: >=3.9,<3.12
Classifier: License :: OSI Approved :: Apache Software License
Classifier: Programming Language :: Python :: 3
Classifier: Programming Language :: Python :: 3.9
Classifier: Programming Language :: Python :: 3.10
Classifier: Programming Language :: Python :: 3.11
Requires-Dist: python-dateutil (>=2.8.2,<3.0.0)
Requires-Dist: rdflib (>=6.0.0)
Requires-Dist: unidecode
